notunsplash/__init__.py
notunsplash/attribution.py
notunsplash/client.py
notunsplash/errors.py
notunsplash/models.py
notunsplash-0.1.0.dist-info/LICENSE
notunsplash-0.1.0.dist-info/METADATA
notunsplash-0.1.0.dist-info/WHEEL
notunsplash-0.1.0.dist-info/top_level.txt
notunsplash-0.1.0.dist-info/RECORD
