Metadata-Version: 2.1
Name: notunsplash
Version: 0.1.0
Summary: A Python SDK for the Unsplash API
Home-page: UNKNOWN
Author: Robert Jones
License: UNKNOWN
Platform: UNKNOWN
Requires-Python: >=3.7
License-File: LICENSE
Requires-Dist: requests>=2.31.0
Requires-Dist: python-dateutil>=2.8.2
Requires-Dist: urllib3>=2.0.7
